sfu_torch_lib/__init__.py
sfu_torch_lib/file_fetcher.py
sfu_torch_lib/group_sampler.py
sfu_torch_lib/io.py
sfu_torch_lib/mlflow.py
sfu_torch_lib/modules/__init__.py
sfu_torch_lib/modules/batchrenorm.py
sfu_torch_lib/optimization.py
sfu_torch_lib/parameters.py
sfu_torch_lib/processing.py
sfu_torch_lib/sampling.py
sfu_torch_lib/slack.py
sfu_torch_lib/state.py
sfu_torch_lib/tree.py
sfu_torch_lib/types.py
sfu_torch_lib/utils.py
sfu_torch_lib-0.0.60.dist-info/METADATA
sfu_torch_lib-0.0.60.dist-info/WHEEL
sfu_torch_lib-0.0.60.dist-info/licenses/LICENSE
sfu_torch_lib-0.0.60.dist-info/RECORD
